<annotation>
	<folder>images</folder>
	<filename>N2.jpeg</filename>
	<path>/home/captain/Desktop/webapp/images/N2.jpeg</path>
	<source>
		<database>Unknown</database>
	</source>
	<size>
		<width>3112</width>
		<height>2340</height>
		<depth>3</depth>
	</size>
	<segmented>0</segmented>
	<object>
		<name>number_plate</name>
		<pose>Unspecified</pose>
		<truncated>0</truncated>
		<difficult>0</difficult>
		<bndbox>
			<xmin>1822</xmin>
			<ymin>1736</ymin>
			<xmax>2496</xmax>
			<ymax>1866</ymax>
		</bndbox>
	</object>
</annotation>
